scCAMEL/CamelEvo.py
scCAMEL/CamelGuanACoWig.py
scCAMEL/CamelPrefiltering.py
scCAMEL/CamelSwapline.py
scCAMEL/CamelVicuna.py
scCAMEL/__init__.py
sccamel-0.45b0.dist-info/licenses/LICENSE.txt
sccamel-0.45b0.dist-info/METADATA
sccamel-0.45b0.dist-info/WHEEL
sccamel-0.45b0.dist-info/top_level.txt
sccamel-0.45b0.dist-info/RECORD
