Metadata-Version: 2.4
Name: scCAMEL
Version: 0.45b0
Summary: scCAMEL: single cell Cross- Annotation and Multimodal Estimation on Lineage trajectory;License: GPL version 3;Developed by: Yizhou Hu, Department of Laboratory Medicine, Karolinska Institutet;Tutorials and other informations in :https://sccamel.readthedocs.io/
Home-page: https://sccamel.readthedocs.io/
Author: Yizhou Hu
Author-email: yizhou.hu@ki.se
Classifier: Programming Language :: Python :: 3
Classifier: License :: OSI Approved :: GNU General Public License v3 (GPLv3)
Classifier: Operating System :: Microsoft :: Windows
Classifier: Operating System :: POSIX :: Linux
Classifier: Operating System :: MacOS
Requires-Python: >=3.8
License-File: LICENSE.txt
Requires-Dist: arboreto
Requires-Dist: openpyxl
Requires-Dist: skorch
Requires-Dist: kneed
Requires-Dist: captum
Requires-Dist: scanpy
Dynamic: author
Dynamic: author-email
Dynamic: classifier
Dynamic: description
Dynamic: description-content-type
Dynamic: home-page
Dynamic: license-file
Dynamic: requires-dist
Dynamic: requires-python
Dynamic: summary
